<?xml version="1.0"?>
<menu>
  <item>
    <path>civicrm</path>
    <title>CiviCRM</title>
    <access_callback>CRM_Core_Permission::checkMenu</access_callback>
    <access_arguments>access CiviCRM</access_arguments>
    <page_callback>CRM_HRCore_Page_Error404Checker</page_callback>
    <page_arguments>null</page_arguments>
    <is_ssl>false</is_ssl>
    <weight>0</weight>
  </item>
  <item>
    <path>civicrm/dashboard</path>
    <title>CiviCRM</title>
    <access_callback>CRM_Core_Permission::checkMenu</access_callback>
    <access_arguments>access CiviCRM</access_arguments>
    <page_callback>CRM_HRCore_Page_Error404Checker</page_callback>
    <page_arguments>null</page_arguments>
    <is_ssl>false</is_ssl>
    <weight>0</weight>
  </item>
  <item>
    <path>civicrm/default/dashboard</path>
    <title>CiviCRM</title>
    <access_callback>CRM_Core_Permission::checkMenu</access_callback>
    <access_arguments>access CiviCRM</access_arguments>
    <page_callback>CRM_Contact_Page_DashBoard</page_callback>
    <page_arguments>null</page_arguments>
    <is_ssl>false</is_ssl>
    <weight>0</weight>
  </item>
  <item>
    <path>civicrm/user/create-account</path>
    <page_callback>CRM_HRCore_Form_CreateUserRecordSingleTaskForm</page_callback>
    <title>Create User Account</title>
    <access_arguments>create users</access_arguments>
  </item>
  <item>
     <path>civicrm/hrcore/usermenu</path>
     <title>User Menu</title>
     <page_callback>CRM_HRCore_Page_UserMenu</page_callback>
     <access_arguments>access AJAX API</access_arguments>
  </item>
</menu>
